pymyq/__init__.py
pymyq/__version__.py
pymyq/account.py
pymyq/api.py
pymyq/const.py
pymyq/device.py
pymyq/errors.py
pymyq/garagedoor.py
pymyq/lamp.py
pymyq/lock.py
pymyq/request.py
python_myq-3.1.13.dist-info/LICENSE
python_myq-3.1.13.dist-info/METADATA
python_myq-3.1.13.dist-info/WHEEL
python_myq-3.1.13.dist-info/RECORD
