Metadata-Version: 2.1
Name: python-myq
Version: 3.1.13
Summary: Python package for controlling MyQ-Enabled Garage Door.
Home-page: https://github.com/Python-MyQ/Python-MyQ
License: MIT
Author: Lash-L
Author-email: lukelashley99@gmail.com
Requires-Python: >=3.8,<4.0
Classifier: Development Status :: 5 - Production/Stable
Classifier: Intended Audience :: Developers
Classifier: License :: OSI Approved :: MIT License
Classifier: Natural Language :: English
Classifier: Operating System :: OS Independent
Classifier: Programming Language :: Python :: 3
Classifier: Programming Language :: Python :: 3.8
Classifier: Programming Language :: Python :: 3.9
Classifier: Programming Language :: Python :: 3.10
Classifier: Programming Language :: Python :: 3.11
Classifier: Topic :: Software Development :: Libraries
Requires-Dist: aiohttp (>=3.7,<4.0)
Requires-Dist: beautifulsoup4 (>=4.9.3,<5.0.0)
Requires-Dist: pkce (>=1.0.2,<2.0.0)
Project-URL: Repository, https://github.com/Python-MyQ/Python-MyQ
